hident/__init__.py
hident/hident.py
hident-0.1.7.dist-info/entry_points.txt
hident-0.1.7.dist-info/WHEEL
hident-0.1.7.dist-info/METADATA
hident-0.1.7.dist-info/RECORD
