Metadata-Version: 2.1
Name: hident
Version: 0.1.7
Summary: 
Author: Mark A. Miller
Author-email: mamillerpa@gmail.com
Requires-Python: >=3.9,<4.0
Classifier: Programming Language :: Python :: 3
Classifier: Programming Language :: Python :: 3.9
Requires-Dist: click
Requires-Dist: click-log
Requires-Dist: pandas (>=1.3.5,<2.0.0)
Requires-Dist: prefixcommons (>=0.1.9,<0.2.0)
